uxr/__init__.py
uxr/utils.py
uxr/length/__init__.py
uxr/length/api.py
uxr/length/core.py
uxr-0.1.0.dist-info/LICENSE
uxr-0.1.0.dist-info/METADATA
uxr-0.1.0.dist-info/WHEEL
uxr-0.1.0.dist-info/top_level.txt
uxr-0.1.0.dist-info/RECORD
