Metadata-Version: 2.1
Name: uxr
Version: 0.1.0
Summary: Quantiative User Experience Research
Home-page: UNKNOWN
Author: Joe Chelladurai
License: UNKNOWN
Platform: UNKNOWN
Requires-Python: >=2.7, !=3.0.*, !=3.1*
License-File: LICENSE
Requires-Dist: pandas (>=1.0)
Requires-Dist: scipy (==1.1)
Requires-Dist: matplotlib (<3,>=2.2.1)
